npeccv6/.\logs	ensorboard\2024.11.29-12.54/train/events.out.tfevents.1732884856.93aacc538777.9426.0.v2
npeccv6/.\logs	ensorboard\2024.11.29-12.54/train/events.out.tfevents.1732884870.93aacc538777.9426.2.v2
npeccv6/.\logs	ensorboard\2024.11.29-12.54/train/events.out.tfevents.1732884899.93aacc538777.9892.0.v2
npeccv6/.\logs	ensorboard\2024.11.29-12.54/validation/events.out.tfevents.1732884867.93aacc538777.9426.1.v2
npeccv6/.\logs	ensorboard\2024.11.29-12.54/validation/events.out.tfevents.1732884880.93aacc538777.9426.3.v2
npeccv6/.\logs	ensorboard\2024.11.29-12.54/validation/events.out.tfevents.1732884910.93aacc538777.9892.1.v2
npeccv6/.\logs	ensorboard\2024.11.29-12.55/train/events.out.tfevents.1732884913.93aacc538777.9892.2.v2
npeccv6/.\logs	ensorboard\2024.11.29-12.55/validation/events.out.tfevents.1732884923.93aacc538777.9892.3.v2
npeccv6/.\logs\tensorboard\2024.10.30-11.11/train/events.out.tfevents.1730286671.93aacc538777.5011.0.v2
npeccv6/.\logs\tensorboard\2024.10.30-11.36/train/events.out.tfevents.1730288164.93aacc538777.9243.0.v2
npeccv6/.\logs\tensorboard\2024.11.11-09.12/train/events.out.tfevents.1731316328.93aacc538777.13609.0.v2
npeccv6/.\logs\tensorboard\2024.11.11-09.12/validation/events.out.tfevents.1731318183.93aacc538777.13609.1.v2
npeccv6/.\logs\tensorboard\2024.11.11-09.54/train/events.out.tfevents.1731318878.93aacc538777.19686.0.v2
npeccv6/.\logs\tensorboard\2024.11.11-09.54/validation/events.out.tfevents.1731320732.93aacc538777.19686.1.v2
npeccv6/.\logs\tensorboard\2024.11.14-12.23/train/events.out.tfevents.1731587006.93aacc538777.20424.0.v2
npeccv6/.\logs\tensorboard\2024.11.14-12.23/validation/events.out.tfevents.1731588861.93aacc538777.20424.1.v2
npeccv6/.\logs\tensorboard\2024.11.14-13.11/train/events.out.tfevents.1731589881.93aacc538777.27604.0.v2
npeccv6/.\logs\tensorboard\2024.11.14-13.11/validation/events.out.tfevents.1731591744.93aacc538777.27604.1.v2
npeccv6-0.1.10.dist-info/METADATA
npeccv6-0.1.10.dist-info/WHEEL
npeccv6-0.1.10.dist-info/entry_points.txt
npeccv6-0.1.10.dist-info/RECORD
