Metadata-Version: 2.1
Name: npeccv6
Version: 0.1.10
Summary: Python package for root recognition and robot controll
Author: Hubert Waleńczak
Author-email: 220817@buas.nl
Requires-Python: >=3.11,<3.12
Classifier: Programming Language :: Python :: 3
Classifier: Programming Language :: Python :: 3.11
Requires-Dist: azure-ai-ml (>=1.16.1,<2.0.0)
Requires-Dist: azureml-core (>=1.56.0,<2.0.0)
Requires-Dist: azureml-dataprep (>=5.1.6,<6.0.0)
Requires-Dist: azureml-defaults (>=1.56.0.post1,<2.0.0)
Requires-Dist: azureml-mlflow (>=1.56.0,<2.0.0)
Requires-Dist: black (>=24.4.2,<25.0.0)
Requires-Dist: datetime (>=5.5,<6.0)
Requires-Dist: fastapi (>=0.111.0,<0.112.0)
Requires-Dist: flake8 (>=7.0.0,<8.0.0)
Requires-Dist: isort (>=5.13.2,<6.0.0)
Requires-Dist: keras (>=2.14,<3.0)
Requires-Dist: mlflow (>=2.13.2,<3.0.0)
Requires-Dist: networkx (>=3.3)
Requires-Dist: numpy (>=1.19.3,<2.0.0)
Requires-Dist: opencv-python (>=4.9.0.80,<5.0.0.0)
Requires-Dist: optuna (>=4.0.0,<5.0.0)
Requires-Dist: patchify (>=0.2.3,<0.3.0)
Requires-Dist: pre-commit (>=3.7.1,<4.0.0)
Requires-Dist: pytest (>=8.2.0)
Requires-Dist: pytest-cov (>=5.0.0)
Requires-Dist: python-runit (>=0.3.0,<0.4.0)
Requires-Dist: requests (>=2.32.3,<3.0.0)
Requires-Dist: skan (>=0.11.1)
Requires-Dist: sphinx (>=7.3.7)
Requires-Dist: sphinx-rtd-theme (>=2.0.0)
Requires-Dist: streamlit (>=1.35.0,<2.0.0)
Requires-Dist: tensorflow (>=2.14.0,<3.0.0)
Requires-Dist: tensorflow-io-gcs-filesystem (>=0.31.0,<0.32.0)
Requires-Dist: uvicorn (>=0.29.0,<0.30.0)
